crontab_py/__init__.py
crontab_py/_routing.py
crontab_py/_version.py
crontab_py/crontab.py
crontab_py/utils/__init__.py
crontab_py/utils/errors.py
crontab_py-0.0.5.dist-info/METADATA
crontab_py-0.0.5.dist-info/WHEEL
crontab_py-0.0.5.dist-info/top_level.txt
crontab_py-0.0.5.dist-info/RECORD
