Metadata-Version: 2.1
Name: crontab-py
Version: 0.0.5
Summary: cron tab handler
Author: Marc anglisano
Author-email: marcanglisano@gmail.com
Project-URL: Documentation, https://anglisano.github.io/crontab_py/
Project-URL: Bug Reports, https://github.com/anglisano/crontab_py/issues
Project-URL: Source, https://github.com/anglisano/crontab_py.git
Classifier: Programming Language :: Python :: 3
Classifier: Operating System :: OS Independent
Requires-Python: >=3.8
